src_files/PC_Adder.v
module PC_Adder(a,b,c);
    input [31:0] a,b;
    output [31:0] c;

    assign c = a + b;
    
endmodule

src_files/Instruction_Memory.v
module Instruction_Memory(rst, A, RD);
    input rst;
    input [31:0] A;
    output [31:0] RD;

    reg [31:0] mem [1023:0];
    assign RD = (rst == 1'b0) ? {32{1'b0}}:mem[A[31:2]];

    initial begin
        $readmemh("memfile.hex", mem);
    end
endmodule

src_files/PC.v
module PC_module(clk, rst, PC, PC_Next);
    input clk, rst;
    input [31:0] PC_Next;
    output reg [31:0] PC;

    always @(posedge clk) begin
        if(~(rst))
            PC <= {32{1'b0}};
        else
            PC <= PC_Next;
    end
endmodule

src_files/mux.v
module mux(a,b,s,c);
    input [31:0] a,b;
    input s;
    output [31:0] c;

    assign c = (~s) ? a:b;
endmodule

module mux_3_by_1(a,b,c,s,d);
    input [31:0] a,b,c;
    input [1:0] s;
    output [31:0] d;

    assign d = (s == 2'b00) ? a : ((s == 2'b01) ? b : ((s == 2'b10) ? c : 32'b0));
endmodule

src_files/Fetch_Cycle.v
module fetch_cycle(clk, rst, PCSrcE, PCTargetE, InstrD, PCD, PCPlus4D);
    
    //input and outputs declaring
    input clk, rst;
    input PCSrcE;
    input [31:0] PCTargetE;
    output [31:0] InstrD;
    output [31:0] PCD, PCPlus4D;

    //declaring the interim wires
    wire [31:0] PC_F, PCF, PCPlus4F;
    wire [31:0] InstrF;

    //declaring the registers
    reg [31:0] InstrF_reg;
    reg [31:0] PCF_reg, PCPlus4F_reg;

    //instantiation of modules
    //PC MUX
    mux PC_MUX (.a(PCPlus4F),
                .b(PCTargetE),
                .s(PCSrcE),
                .c(PC_F));

    //PC Counter
    PC_module Program_Counter (.clk(clk), 
                                .rst(rst), 
                                .PC(PCF), 
                                .PC_Next(PC_F));

    //declare instruction memory
    Instruction_Memory IMEM (.rst(rst), 
                            .A(PCF), 
                            .RD(InstrF));

    //declaring PC Adder
    PC_Adder PC_adder (.a(PCF),
                        .b(32'h00000004),
                        .c(PCPlus4F));

    //fetch cycle register logic
    always @(posedge clk or negedge rst) begin
        if(rst == 1'b0) begin
            InstrF_reg <= 32'h00000000;
            PCF_reg <= 32'h00000000;
            PCPlus4F_reg <= 32'h00000000;
        end
        else begin
            InstrF_reg <= InstrF;
            PCF_reg <= PCF;
            PCPlus4F_reg <= PCPlus4F;
        end
    end

    //assigning register values to the output port
    assign InstrD = InstrF_reg;
    assign PCD = PCF_reg;
    assign PCPlus4D = PCPlus4F_reg;
endmodule

tb_files/Fetch_Cycle_tb.v
`include "Fetch_Cycle.v"
`timescale 1ns/1ns

module tb();

    //declaring the I/Os
    reg clk = 0, rst, PCSrcE;
    reg [31:0] PCTargetE;
    wire [31:0] InstrD, PCD, PCPlus4D;
    
    //declaring the design under test
    fetch_cycle dut (.clk(clk), 
                    .rst(rst), 
                    .PCSrcE(PCSrcE), 
                    .PCTargetE(PCTargetE), 
                    .InstrD(InstrD), 
                    .PCD(PCD), 
                    .PCPlus4D(PCPlus4D));
    
    //generation of clock
    always begin
        clk = ~clk;
        #50;
    end

    //providing the stimulus
    initial begin
        rst <= 1'b0;
        #200;
        rst <= 1'b1;
        PCSrcE <= 1'b0;
        PCTargetE <= 32'h00000000;
        #500;
        $finish;
    end

    //generation of vcd file
    initial begin
        $dumpfile("dumpf.vcd");
        $dumpvars(0, tb);
    end
endmodule

tb_files/dumpf.vcd
$date
	Thu Jul 03 23:51:00 2025
$end
$version
	Icarus Verilog
$end
$timescale
	1ns
$end
$scope module tb $end
$var wire 32 ! InstrD [31:0] $end
$var wire 32 " PCD [31:0] $end
$var wire 32 # PCPlus4D [31:0] $end
$var reg 1 $ PCSrcE $end
$var reg 32 % PCTargetE [31:0] $end
$var reg 1 & clk $end
$var reg 1 ' rst $end
$scope module dut $end
$var wire 32 ( InstrD [31:0] $end
$var wire 32 ) InstrF [31:0] $end
$var wire 32 * PCD [31:0] $end
$var wire 32 + PCF [31:0] $end
$var wire 32 , PCPlus4D [31:0] $end
$var wire 32 - PCPlus4F [31:0] $end
$var wire 1 . PCSrcE $end
$var wire 32 / PCTargetE [31:0] $end
$var wire 32 0 PC_F [31:0] $end
$var wire 1 1 clk $end
$var wire 1 2 rst $end
$var reg 32 3 InstrF_reg [31:0] $end
$var reg 32 4 PCF_reg [31:0] $end
$var reg 32 5 PCPlus4F_reg [31:0] $end
$scope module PC_MUX $end
$var wire 32 6 a [31:0] $end
$var wire 32 7 b [31:0] $end
$var wire 32 8 c [31:0] $end
$var wire 1 . s $end
$upscope $end
$scope module Program_Counter $end
$var wire 32 9 PC_Next [31:0] $end
$var wire 1 1 clk $end
$var wire 1 2 rst $end
$var reg 32 : PC [31:0] $end
$upscope $end
$scope module IMEM $end
$var wire 32 ; A [31:0] $end
$var wire 32 < RD [31:0] $end
$var wire 1 2 rst $end
$upscope $end
$scope module PC_adder $end
$var wire 32 = a [31:0] $end
$var wire 32 > b [31:0] $end
$var wire 32 ? c [31:0] $end
$upscope $end
$upscope $end
$upscope $end
$enddefinitions $end
#0
$dumpvars
bx ?
b100 >
bx =
b0 <
bx ;
bx :
bx 9
bx 8
bx 7
bx 6
b0 5
b0 4
b0 3
02
11
bx 0
bx /
x.
bx -
b0 ,
bx +
b0 *
b0 )
b0 (
0'
1&
bx %
x$
b0 #
b0 "
b0 !
$end
#50
0&
01
#100
b0 :
b100 -
b100 6
b100 ?
b0 +
b0 ;
b0 =
1&
11
#150
0&
01
#200
b10100000000001010010011 )
b10100000000001010010011 <
b100 0
b100 8
b100 9
b0 %
b0 /
b0 7
0$
0.
1'
12
1&
11
#250
0&
01
#300
b1100000000001100010011 )
b1100000000001100010011 <
b1000 0
b1000 8
b1000 9
b100 :
b1000 -
b1000 6
b1000 ?
b100 +
b100 ;
b100 =
b100 5
b100 #
b100 ,
b10100000000001010010011 3
b10100000000001010010011 !
b10100000000001010010011 (
1&
11
#350
0&
01
#400
b11000101000001110110011 )
b11000101000001110110011 <
b1100 0
b1100 8
b1100 9
b1000 :
b1100 -
b1100 6
b1100 ?
b1000 +
b1000 ;
b1000 =
b1000 5
b1000 #
b1000 ,
b100 4
b100 "
b100 *
b1100000000001100010011 3
b1100000000001100010011 !
b1100000000001100010011 (
1&
11
#450
0&
01
#500
b10010000000011 )
b10010000000011 <
b10000 0
b10000 8
b10000 9
b1100 :
b10000 -
b10000 6
b10000 ?
b1100 +
b1100 ;
b1100 =
b1100 5
b1100 #
b1100 ,
b1000 4
b1000 "
b1000 *
b11000101000001110110011 3
b11000101000001110110011 !
b11000101000001110110011 (
1&
11
#550
0&
01
#600
b100000000010010010011 )
b100000000010010010011 <
b10100 0
b10100 8
b10100 9
b10000 :
b10100 -
b10100 6
b10100 ?
b10000 +
b10000 ;
b10000 =
b10000 5
b10000 #
b10000 ,
b1100 4
b1100 "
b1100 *
b10010000000011 3
b10010000000011 !
b10010000000011 (
1&
11
#650
0&
01
#700
b100101000000010100110011 )
b100101000000010100110011 <
b11000 0
b11000 8
b11000 9
b10100 :
b11000 -
b11000 6
b11000 ?
b10100 +
b10100 ;
b10100 =
b10100 5
b10100 #
b10100 ,
b10000 4
b10000 "
b10000 *
b100000000010010010011 3
b100000000010010010011 !
b100000000010010010011 (
1&
11
